lark_notice/__init__.py
lark_notice/lark_noticer.py
lark_notice-0.1.0.dist-info/METADATA
lark_notice-0.1.0.dist-info/WHEEL
lark_notice-0.1.0.dist-info/RECORD
